MANIFEST.in
README.rst
setup.py
bin/test
docs/Makefile
docs/api.rst
docs/conf.py
docs/index.rst
docs/installation.rst
docs/introduction.rst
docs/javascript_api.rst
docs/python_api.rst
docs/pymodules/cameras.rst
docs/pymodules/lights.rst
docs/pymodules/scene.rst
docs/pymodules/shapes.rst
docs/pymodules/visualization_frame.rst
pydy_viz/__init__.py
pydy_viz/camera.py
pydy_viz/light.py
pydy_viz/scene.py
pydy_viz/server.py
pydy_viz/shapes.py
pydy_viz/visualization_frame.py
pydy_viz.egg-info/PKG-INFO
pydy_viz.egg-info/SOURCES.txt
pydy_viz.egg-info/dependency_links.txt
pydy_viz.egg-info/requires.txt
pydy_viz.egg-info/top_level.txt
pydy_viz/static/index.html
pydy_viz/static/css/bootstrap.min.css
pydy_viz/static/css/style.css
pydy_viz/static/js/SpecRunner.html
pydy_viz/static/js/canvas/addObjects.js
pydy_viz/static/js/canvas/animate.js
pydy_viz/static/js/canvas/initialize.js
pydy_viz/static/js/jasmine/MIT.LICENSE
pydy_viz/static/js/jasmine/jasmine-html.js
pydy_viz/static/js/jasmine/jasmine.css
pydy_viz/static/js/jasmine/jasmine.js
pydy_viz/static/js/lib/LICENCE
pydy_viz/static/js/lib/LICENCE.MIT
pydy_viz/static/js/lib/TrackballControls.js
pydy_viz/static/js/lib/blanket.min.js
pydy_viz/static/js/lib/bootstrap.min.js
pydy_viz/static/js/lib/jasmine-blanket.js
pydy_viz/static/js/lib/jquery-ui.js
pydy_viz/static/js/lib/jquery.min.js
pydy_viz/static/js/lib/three.min.js
pydy_viz/static/js/specs/canvasSpecs.js
pydy_viz/static/js/specs/specHelper.js
pydy_viz/tests/__init__.py
pydy_viz/tests/test_shapes.py
pydy_viz/tests/test_socket_server.py
pydy_viz/tests/test_visualization_frame_scene.py