Metadata-Version: 1.1
Name: pydy-viz
Version: 0.1.0
Summary: Browser based 3D visualization of multibody simulations.
Home-page: https://github.com/pydy/pydy-viz/
Author: Tarun Gaba
Author-email: tarun.gaba7@gmail.com
License: LICENSE.txt
Keywords: dynamics multibody simulation visualization
Platform: UNKNOWN
Classifier: Development Status :: 3 - Alpha
Classifier: Intended Audience :: Science/Research
Classifier: Operating System :: OS Independent
Classifier: Programming Language :: Python :: 2.7
Classifier: Topic :: Scientific/Engineering :: Physics
